django_mongoengine_logger/__init__.py
django_mongoengine_logger/documents.py
django_mongoengine_logger/logging.py
django_mongoengine_logger-0.1.1.dist-info/LICENSE
django_mongoengine_logger-0.1.1.dist-info/METADATA
django_mongoengine_logger-0.1.1.dist-info/WHEEL
django_mongoengine_logger-0.1.1.dist-info/RECORD
