Metadata-Version: 2.1
Name: django-mongoengine-logger
Version: 0.1.1
Summary: A Django logger that logs to MongoDB using MongoEngine.
License: MIT
Author: Hamzeh Pourmahdi
Author-email: hpourmahdi@hotmail.com
Requires-Python: >=3.11,<4.0
Classifier: License :: OSI Approved :: MIT License
Classifier: Programming Language :: Python :: 3
Classifier: Programming Language :: Python :: 3.11
Classifier: Programming Language :: Python :: 3.12
Requires-Dist: django (==4.2)
Requires-Dist: mongoengine (>=0.29.0,<0.30.0)
